ncatbot/__init__.py
ncatbot/cli/__init__.py
ncatbot/cli/main.py
ncatbot/cli/commands/__init__.py
ncatbot/cli/commands/config_commands.py
ncatbot/cli/commands/info_commands.py
ncatbot/cli/commands/permission_commands.py
ncatbot/cli/commands/plugin_commands.py
ncatbot/cli/commands/registry.py
ncatbot/cli/commands/system_commands.py
ncatbot/cli/utils/__init__.py
ncatbot/cli/utils/cli_exceptions.py
ncatbot/cli/utils/colors.py
ncatbot/cli/utils/constants.py
ncatbot/cli/utils/pip_tool.py
ncatbot/cli/utils/plugin_utils.py
ncatbot/core/__init__.py
ncatbot/core/client.py
ncatbot/core/adapter/__init__.py
ncatbot/core/adapter/adapter.py
ncatbot/core/adapter/nc/__init__.py
ncatbot/core/adapter/nc/config.py
ncatbot/core/adapter/nc/install.py
ncatbot/core/adapter/nc/launch.py
ncatbot/core/adapter/nc/login.py
ncatbot/core/adapter/nc/start.py
ncatbot/core/adapter/nc/utils.py
ncatbot/core/api/__init__.py
ncatbot/core/api/api.py
ncatbot/core/api/api_account.py
ncatbot/core/api/api_group.py
ncatbot/core/api/api_message.py
ncatbot/core/api/api_private.py
ncatbot/core/api/api_support.py
ncatbot/core/api/utils.py
ncatbot/core/event/PokeNoticeEvent.py
ncatbot/core/event/__init__.py
ncatbot/core/event/event_data.py
ncatbot/core/event/message.py
ncatbot/core/event/meta.py
ncatbot/core/event/notice.py
ncatbot/core/event/request.py
ncatbot/core/event/sender.py
ncatbot/core/event/message_segment/__init__.py
ncatbot/core/event/message_segment/message_array.py
ncatbot/core/event/message_segment/message_segment.py
ncatbot/core/event/message_segment/sentence.py
ncatbot/core/event/message_segment/utils.py
ncatbot/core/helper/__init__.py
ncatbot/core/helper/forward_constructor.py
ncatbot/core/message/__init__.py
ncatbot/mcp/__init__.py
ncatbot/mcp/main.py
ncatbot/plugin/__init__.py
ncatbot/plugin/compatible_enrollment.py
ncatbot/plugin_system/__init__.py
ncatbot/plugin_system/base_plugin.py
ncatbot/plugin_system/config.py
ncatbot/plugin_system/decorator.py
ncatbot/plugin_system/deprecated.py
ncatbot-4.4.1.post1.dist-info/licenses/LICENSE
ncatbot-4.4.1.post1.dist-info/licenses/NOTICE
ncatbot-4.4.1.post1.dist-info/METADATA
ncatbot-4.4.1.post1.dist-info/WHEEL
ncatbot-4.4.1.post1.dist-info/entry_points.txt
ncatbot-4.4.1.post1.dist-info/top_level.txt
ncatbot-4.4.1.post1.dist-info/RECORD
