Metadata-Version: 2.4
Name: ncatbot
Version: 4.4.1.post1
Summary: NcatBot，基于协议的QQ机器人Python SDK
Home-page: https://github.com/liyihao1110/ncatbot
Author: 木子
Author-email: lyh_02@qq.com
License: MIT
Project-URL: Source, https://github.com/liyihao1110/ncatbot
Project-URL: Bug Reports, https://github.com/liyihao1110/ncatbot/issues
Project-URL: Documentation, https://github.com/liyihao1110/ncatbot/wiki
Classifier: Development Status :: 4 - Beta
Classifier: Intended Audience :: Developers
Classifier: License :: OSI Approved :: MIT License
Classifier: Programming Language :: Python :: 3.8
Classifier: Programming Language :: Python :: 3.9
Classifier: Programming Language :: Python :: 3.10
Classifier: Programming Language :: Python :: 3.11
Classifier: Programming Language :: Python :: 3.12
Classifier: Operating System :: OS Independent
Classifier: Topic :: Software Development :: Libraries :: Python Modules
Requires-Python: >=3.8
License-File: LICENSE
License-File: NOTICE
Requires-Dist: toml
Requires-Dist: qrcode
Requires-Dist: schedule
Requires-Dist: urllib3
Requires-Dist: websockets
Requires-Dist: packaging
Requires-Dist: rich
Requires-Dist: aiofiles
Requires-Dist: typing-extensions
Requires-Dist: colorama>=0.4.6; platform_system == "Windows"
Requires-Dist: importlib-metadata>=8.6.1; python_version >= "3.9"
Requires-Dist: importlib-metadata>=4.0; python_version < "3.9"
Requires-Dist: httpx>=0.28.1
Requires-Dist: psutil>=6.1.1
Requires-Dist: pyyaml>=6.0.2
Requires-Dist: requests>=2.32.3
Requires-Dist: tqdm>=4.67.1
Dynamic: author
Dynamic: author-email
Dynamic: classifier
Dynamic: description
Dynamic: description-content-type
Dynamic: home-page
Dynamic: license
Dynamic: license-file
Dynamic: project-url
Dynamic: requires-dist
Dynamic: requires-python
Dynamic: summary
